ART/ARTmain.py
ART/DefaultOptions.py
ART/ModuleAnalysisAndPlots.py
ART/__init__.py
AttosecondRayTracing-0.92.dist-info/LICENSE
AttosecondRayTracing-0.92.dist-info/METADATA
AttosecondRayTracing-0.92.dist-info/WHEEL
AttosecondRayTracing-0.92.dist-info/top_level.txt
AttosecondRayTracing-0.92.dist-info/RECORD
